flecsimo/__init__.py
flecsimo/app/__init__.py
flecsimo/app/area_agent.py
flecsimo/app/area_control.py
flecsimo/app/cell_agent.py
flecsimo/app/site_agent.py
flecsimo/app/site_control.py
flecsimo/app/station_control.py
flecsimo/base/__init__.py
flecsimo/base/config.py
flecsimo/base/connect.py
flecsimo/base/const.py
flecsimo/base/logger.py
flecsimo/base/msg.py
flecsimo/base/states.py
flecsimo/conf/__init__.py
flecsimo/conf/config.json
flecsimo/conf/config_area.json
flecsimo/conf/config_cell-1.json
flecsimo/conf/config_cell-2.json
flecsimo/conf/config_cell-3.json
flecsimo/conf/config_cell-4.json
flecsimo/conf/config_cell.json
flecsimo/conf/config_site.json
flecsimo/db/__init__.py
flecsimo/db/area.db
flecsimo/db/cell-1.db
flecsimo/db/cell-2.db
flecsimo/db/cell-3.db
flecsimo/db/cell-4.db
flecsimo/db/cell.db
flecsimo/db/site.db
flecsimo/roles/__init__.py
flecsimo/roles/callback.py
flecsimo/roles/controller.py
flecsimo/roles/enrolment.py
flecsimo/util/__init__.py
flecsimo-0.1.3.data/scripts/area_agent.py
flecsimo-0.1.3.data/scripts/area_control.py
flecsimo-0.1.3.data/scripts/cell_agent.py
flecsimo-0.1.3.data/scripts/site_agent.py
flecsimo-0.1.3.data/scripts/site_control.py
flecsimo-0.1.3.data/scripts/station_control.py
flecsimo-0.1.3.dist-info/LICENSE
flecsimo-0.1.3.dist-info/METADATA
flecsimo-0.1.3.dist-info/WHEEL
flecsimo-0.1.3.dist-info/top_level.txt
flecsimo-0.1.3.dist-info/RECORD
