Metadata-Version: 2.1
Name: flecsimo
Version: 0.1.3
Summary: A research/educational simulation model of a IIoT cellular production site.
Home-page: https://gitlab.com/flecsimodev/flecsimo
Author: Ralf Banning, Bernhard Lehner
Author-email: banning@fb3.fra-uas.de
Maintainer: Ralf Banning
Maintainer-email: banning@fb3.fra-uas.de
License: GPLv3+
Project-URL: Documentation, https://confluence.frankfurt-university.de/display/FFP
Project-URL: Source, https://gitlab.com/flecsimodev/flecsimo
Project-URL: Tracker, https://gitlab.com/flecsimodev/flecsimo/-/issues
Keywords: cellular manufacturing,simulation,IIoT
Platform: UNKNOWN
Classifier: Development Status :: 3 - Alpha
Classifier: Intended Audience :: End Users/Desktop
Classifier: Intended Audience :: Developers
Classifier: Intended Audience :: System Administrators
Classifier: Topic :: Education
Classifier: Topic :: Scientific/Engineering
Classifier: License :: OSI Approved :: GNU General Public License v3 or later (GPLv3+)
Classifier: Programming Language :: Python :: 3 :: Only
Classifier: Programming Language :: Python :: 3.6
Classifier: Programming Language :: Python :: 3.7
Classifier: Programming Language :: Python :: 3.8
Classifier: Operating System :: POSIX :: Linux
Classifier: Operating System :: Microsoft :: Windows :: Windows 10
Requires-Python: >=3.6, <4
Requires-Dist: paho-mqtt (>=1.5.0)
Requires-Dist: transitions (>=0.8.1)
Requires-Dist: memory-profiler (>=0.57.0)
Requires-Dist: pyreadline (>=2.1)
